sixteen/__init__.py
sixteen/__version__.py
sixteen-0.1.0.dist-info/LICENSE
sixteen-0.1.0.dist-info/METADATA
sixteen-0.1.0.dist-info/WHEEL
sixteen-0.1.0.dist-info/top_level.txt
sixteen-0.1.0.dist-info/RECORD
